{
  "header": {
    "toggleNavigation": {
      "attributes": {
        "id": "application-toggle-navigation",
        "class": "navigation toggle-navigation"
      },
      "toggle": {
        "textContent": "*",
        "attributes": {
          "id": "application-toggle-navigation-toggle-button",
          "class": "button toggle-button",
          "data-action": "toggle-visible",
          "data-target": "#application-toggle-navigation-subnavigation",
          "data-secondary-action": "toggle-active",
          "data-secondary-target": "#application-toggle-navigation-toggle-button"
        }
      },
      "subnavigation": {
        "attributes": {
          "id": "application-toggle-navigation-subnavigation",
          "class": "navigation subnavigation",
          "data-visible": false
        },
        "buttons": [
          {
            "_auth": true,
            "_no_auth": false,
            "textContent": "Profile",
            "attributes": {
              "class": "button subnavigation-button",
              "data-href": "/account/profile",
              "data-target": "_self"
            }
          },
          {
            "_auth": true,
            "_no_auth": false,
            "class": "subnavigation-button",
            "textContent": "Photos",
            "attributes": {
              "class": "button subnavigation-button",
              "data-href": "/photos",
              "data-target": "_self"
            }
          },
          {
            "_auth": true,
            "_no_auth": false,
            "class": "subnavigation-button",
            "textContent": "Favorited",
            "attributes": {
              "class": "button subnavigation-button",
              "data-href": "/favorites",
              "data-target": "_self"
            }
          },
          {
            "_auth": true,
            "_no_auth": false,
            "class": "subnavigation-button",
            "textContent": "Voted",
            "attributes": {
              "class": "button subnavigation-button",
              "data-href": "/votes",
              "data-target": "_self"
            }
          },
          {
            "_auth": true,
            "_no_auth": false,
            "class": "subnavigation-button",
            "textContent": "Upload",
            "attributes": {
              "class": "button subnavigation-button",
              "data-href": "/upload",
              "data-target": "_self"
            }
          },
          {
            "_auth": false,
            "_no_auth": true,
            "class": "subnavigation-button",
            "textContent": "Login",
            "attributes": {
              "class": "button subnavigation-button",
              "data-href": "/account/login",
              "data-target": "_self"
            }
          },
          {
            "_auth": true,
            "_no_auth": false,
            "class": "subnavigation-button",
            "textContent": "Logout",
            "attributes": {
              "class": "button subnavigation-button",
              "data-href": "account/logout",
              "data-target": "_self"
            }
          }
        ]
      }
    }
  }
}