{
  "/": {
    "name": "Index",
    "callback": "loadModule"
  },
  "/account/login": {
    "name": "Login",
    "callback": "loadModule"
  },
  "/account/logout": {
    "name": "Logout",
    "callback": "loadModule"
  },
  "/account/profile": {
    "name": "Profile",
    "callback": "loadModule"
  },
  "/photos": {
    "name": "Photos",
    "callback": "loadModule"
  },
  "/photos/:photo": {
    "name": "Photo",
    "callback": "loadModule"
  },
  "/favorites": {
    "name": "Favorites",
    "callback": "loadModule"
  },
  "/favorites/:favorite": {
    "name": "Favorite",
    "callback": "loadModule"
  },
  "/upload": {
    "name": "Upload",
    "callback": "loadModule"
  }
}